sense_hat/__init__.py
sense_hat/colour.py
sense_hat/exceptions.py
sense_hat/sense_hat.py
sense_hat/sense_hat_text.png
sense_hat/sense_hat_text.txt
sense_hat/stick.py
sense_hat-2.4.0.dist-info/LICENCE.txt
sense_hat-2.4.0.dist-info/METADATA
sense_hat-2.4.0.dist-info/WHEEL
sense_hat-2.4.0.dist-info/top_level.txt
sense_hat-2.4.0.dist-info/RECORD
