Metadata-Version: 2.1
Name: sense-hat
Version: 2.4.0
Summary: Python module to control the Raspberry Pi Sense HAT, originally used in the Astro Pi mission
Home-page: https://github.com/astro-pi/python-sense-hat
Author: Dave Honess
Author-email: dave@raspberrypi.org
License: BSD
Keywords: sense hat,raspberrypi,astro pi
Platform: UNKNOWN
Classifier: Development Status :: 5 - Production/Stable
Classifier: Programming Language :: Python :: 2
Classifier: Programming Language :: Python :: 3
Classifier: Topic :: Scientific/Engineering :: Astronomy
Classifier: Topic :: Scientific/Engineering :: Atmospheric Science
Classifier: Topic :: Education
Classifier: Intended Audience :: Education
Classifier: Intended Audience :: Science/Research
Classifier: License :: OSI Approved :: BSD License
License-File: LICENCE.txt
Requires-Dist: pillow
Requires-Dist: numpy
